aaf/__init__.py
aaf/chat.py
aaf/event_handlers.py
aaf/forwarding.py
aaf/logging.py
aaf/prompts.py
aaf/threads.py
aaf/ui.py
aaf/utils.py
aaf/llms/__init__.py
aaf/llms/anthropic.py
aaf/llms/base.py
aaf/llms/litellm.py
aaf/llms/ollama.py
aaf/llms/openai.py
aaf/llms/openrouter.py
aaf/llms/types.py
aaf/proxy/__init__.py
aaf/proxy/app.py
aaf/tools/__init__.py
aaf/tools/demo.py
aaf/tools/web.py
aaf/tools_support/__init__.py
aaf/tools_support/schema.py
aaf/virtual_models/__init__.py
aaf/virtual_models/base.py
aaf/virtual_models/demos.py
aaf/virtual_models/multiphase.py
aaf/virtual_models/router.py
aaf/virtual_models/two_phase.py
aaf/virtual_models/types.py
aaf-0.3.10.dist-info/METADATA
aaf-0.3.10.dist-info/WHEEL
aaf-0.3.10.dist-info/licenses/LICENSE
aaf-0.3.10.dist-info/RECORD
