Metadata-Version: 2.4
Name: aaf
Version: 0.3.10
Summary: AAF (Agentic AI Framework)
Author-email: Rivo Laks <hi@rivolaks.com>
License: MIT
License-File: LICENSE
Requires-Python: >=3.12
Requires-Dist: anthropic~=0.37
Requires-Dist: docstring-parser~=0.16
Requires-Dist: duckduckgo-search~=6.2
Requires-Dist: fastapi[standard]~=0.111
Requires-Dist: litellm>=1.80.5
Requires-Dist: openai<3.0,>=1.30
Requires-Dist: prompt-toolkit~=3.0
Requires-Dist: pydantic~=2.7
Requires-Dist: rich~=13.7
Requires-Dist: sse-starlette~=2.1
Requires-Dist: typer~=0.12
Requires-Dist: typing-inspect~=0.9
